coma/__init__.py
coma/config/__init__.py
coma/config/base.py
coma/config/cli.py
coma/config/io.py
coma/core/__init__.py
coma/core/command.py
coma/core/singleton.py
coma/core/wake.py
coma/hooks/__init__.py
coma/hooks/base.py
coma/hooks/config_hook.py
coma/hooks/init_hook.py
coma/hooks/management.py
coma/hooks/parser_hook.py
coma/hooks/run_hook.py
coma-3.0.1.dist-info/LICENSE
coma-3.0.1.dist-info/METADATA
coma-3.0.1.dist-info/WHEEL
coma-3.0.1.dist-info/top_level.txt
coma-3.0.1.dist-info/RECORD
