Metadata-Version: 2.1
Name: coma
Version: 3.0.1
Summary: Configurable command management for humans
Home-page: https://github.com/francois-rd/coma
Author: Francois Roewer-Despres
Author-email: coma.pypi@gmail.com
Project-URL: Bug Tracker, https://github.com/francois-rd/coma/issues
Project-URL: Documentation, https://coma.readthedocs.io
Classifier: Programming Language :: Python :: 3
Classifier: Programming Language :: Python :: 3.9
Classifier: Programming Language :: Python :: 3.10
Classifier: Programming Language :: Python :: 3.11
Classifier: Programming Language :: Python :: 3.12
Classifier: Programming Language :: Python :: 3.13
Classifier: License :: OSI Approved :: MIT License
Classifier: Operating System :: OS Independent
Classifier: Development Status :: 5 - Production/Stable
Classifier: Intended Audience :: Developers
Classifier: Topic :: Software Development :: Libraries :: Python Modules
Requires-Python: >=3.9
License-File: LICENSE
Requires-Dist: boltons
Requires-Dist: omegaconf >=2.1
